
{"inventory":[{"mfg":"3Com","model":"3C16930","description":"ATM Module","qty":"2"},{"mfg":"3Com","model":"3CB9EP8","description":"CoreBuilder 9000 820W Power Supply","qty":"25"},{"mfg":"3Com","model":"3CB9LF36R","description":"Switch 4007 36 Port 10\/100BaseTX Switching Module","qty":"6"},{"mfg":"3Com","model":"3CGBIC92","description":"1000 Base-LX GBIC","qty":"156"},{"mfg":"3M","model":"EMSII","description":"EMS Marker Locator","qty":"3"},{"mfg":"ADC","model":"D1M-1A0019","description":"","qty":"1"},{"mfg":"Anchor","model":"RL-12","description":"ANCHOR REDHEAD 1\/2 MULTI S","qty":"149"},{"mfg":"Andrew","model":"MT-050","description":"Dryline","qty":"1"},{"mfg":"APC","model":"CP50B48NA3","description":"PWRShield 50W 48VDC","qty":"3"},{"mfg":"APC","model":"SU48XLBP","description":"XL 48V Battery Park","qty":"1"},{"mfg":"Apple","model":"Xserve (Intel)","description":"2.66 Ghz  8GB RAM  2 processors 4 cores","qty":"4"},{"mfg":"Apple","model":"Xserve (Intel)","description":"3.0 Ghz  8GB RAM  2 processors 4 cores","qty":"5"},{"mfg":"AT&T","model":"AKM90","description":"T3PQAESAAA","qty":"4"},{"mfg":"AT&T","model":"BCP1","description":"S2:5","qty":"3"},{"mfg":"AT&T","model":"BCP2","description":"S1:4 TSI","qty":"6"},{"mfg":"AT&T","model":"MC90167A1B","description":"12:2","qty":"1"},{"mfg":"AVOCENT","model":"TES0090","description":"TS3000","qty":"7"},{"mfg":"AVOCENT","model":"TS3000","description":"CONSOLE SERVER","qty":"6"},{"mfg":"Cisco","model":"GLC-SX-MM-OEM","description":"","qty":"1"},{"mfg":"Cisco","model":"WS-X3500-XL","description":"Gigastack GBIC","qty":"9"},{"mfg":"Codan","model":"5527","description":"C-Band Converter","qty":"1"},{"mfg":"Comtech","model":"Antenna","description":"5.5M C-Band 3-port linear feed antenna","qty":"1"},{"mfg":"Digital","model":"B3030-ET","description":"B06, A06","qty":"7"},{"mfg":"Digital","model":"B3030-FT","description":"B01","qty":"2"},{"mfg":"Digital","model":"B3030-GH","description":"E01","qty":"1"},{"mfg":"Digital","model":"B3030-GT","description":"E01","qty":"2"},{"mfg":"Digital","model":"B3032-FA","description":"B01","qty":"2"},{"mfg":"Digital","model":"B3032-FL","description":"B01","qty":"3"},{"mfg":"Digital","model":"B3032-FT","description":"B01","qty":"1"},{"mfg":"Digital","model":"B3032-FV","description":"B01","qty":"1"},{"mfg":"Digital","model":"B3032-FV","description":"B01","qty":"3"},{"mfg":"Digital","model":"HSx80","description":"Cache Controller Module","qty":"5"},{"mfg":"Digital","model":"KZPBA-CA","description":"_","qty":"1"},{"mfg":"Digital","model":"KZPCM-DX","description":"_","qty":"2"},{"mfg":"Elco","model":"6x1-1\/4","description":"Drywall Screws","qty":"100"},{"mfg":"Force 10","model":"GP-SFP2-1S MFGR1","description":"GBIC","qty":"14"},{"mfg":"FUJITSU","model":"BP1A02AA","description":"","qty":"2"},{"mfg":"FUJITSU","model":"BP1A37AA","description":"","qty":"1"},{"mfg":"Fujitsu","model":"FC9511AWU1","description":"FLASH-192 ALM & OW","qty":"9"},{"mfg":"Fujitsu","model":"FC9511AWU1","description":"FLASH-192 ALM & OW","qty":"2"},{"mfg":"Fujitsu","model":"FC9511C2S1","description":"","qty":"1"},{"mfg":"Fujitsu","model":"FC9511DSM2","description":"Module","qty":"1"},{"mfg":"Fujitsu","model":"FC9511HED2","description":"FLASH-192 HEADER UNIT","qty":"14"},{"mfg":"Fujitsu","model":"FC9511HUB3","description":"#N\/A","qty":"13"},{"mfg":"Fujitsu","model":"FC9511HUB3","description":"#N\/A","qty":"3"},{"mfg":"Fujitsu","model":"FC9511HUB5","description":"#N\/A","qty":"9"},{"mfg":"FUJITSU","model":"FC9511MEM1","description":"","qty":"13"},{"mfg":"FUJITSU","model":"FC9511MXS1","description":"","qty":"5"},{"mfg":"Fujitsu","model":"FC9511SWR1","description":"","qty":"4"},{"mfg":"Fujitsu","model":"FC9511SWR1","description":"","qty":"2"},{"mfg":"Fujitsu","model":"FC9512AWB1","description":"","qty":"27"},{"mfg":"Fujitsu","model":"FC9512AWU3","description":"","qty":"10"},{"mfg":"Fujitsu","model":"FC9512CPU2","description":"","qty":"1"},{"mfg":"Fujitsu","model":"FC9512CRF4","description":"","qty":"12"},{"mfg":"Fujitsu","model":"FC9512HED4","description":"","qty":"6"},{"mfg":"Fujitsu","model":"FC9512HUB1","description":"","qty":"3"},{"mfg":"Fujitsu","model":"FC9512MEM2","description":"","qty":"5"},{"mfg":"Fujitsu","model":"FC9512MS03","description":"","qty":"6"},{"mfg":"Fujitsu","model":"FC9512MS07","description":"iss-03","qty":"6"},{"mfg":"Fujitsu","model":"FC9512MS19","description":"iss-03","qty":"1"},{"mfg":"Fujitsu","model":"FC9512MS39","description":"","qty":"2"},{"mfg":"Fujitsu","model":"FC9512MS98","description":"","qty":"6"},{"mfg":"Fujitsu","model":"FC9512PWR3","description":"","qty":"13"},{"mfg":"Fujitsu","model":"FC9512VS11","description":"","qty":"1"},{"mfg":"Fujitsu","model":"FC9512VS35","description":"","qty":"1"},{"mfg":"Fujitsu","model":"FC9513B4S1","description":"","qty":"1"},{"mfg":"Fujitsu","model":"FC9520C2B1","description":"heci sn16hecaaa","qty":"1"},{"mfg":"Fujitsu","model":"FC9520C2C2","description":"","qty":"5"},{"mfg":"Fujitsu","model":"FC9520C2D1","description":"","qty":"7"},{"mfg":"FUJITSU","model":"FC9520CPU1","description":"","qty":"2"},{"mfg":"Fujitsu","model":"FC9520D1U1","description":"","qty":"44"},{"mfg":"FUJITSU","model":"FC9520ETH1","description":"","qty":"1"},{"mfg":"Fujitsu","model":"FC9520F2D1","description":"","qty":"2"},{"mfg":"Fujitsu","model":"FC9520F3E1","description":"","qty":"8"},{"mfg":"Fujitsu","model":"FC9520F8C1","description":"","qty":"48"},{"mfg":"FUJITSU","model":"FC9520FAN4","description":"","qty":"8"},{"mfg":"Fujitsu","model":"FC9520MEM1","description":"","qty":"2"},{"mfg":"Fujitsu","model":"FC9520SF11","description":"SNP8704CAA","qty":"6"},{"mfg":"Fujitsu","model":"FC9520SF21","description":"Module","qty":"1"},{"mfg":"FUJITSU","model":"FC9520VF12","description":"","qty":"2"},{"mfg":"Fujitsu","model":"FC9525AAC1","description":"","qty":"6"},{"mfg":"Fujitsu","model":"FC9525HUB1","description":"","qty":"2"},{"mfg":"Fujitsu","model":"FC9525SAC1","description":"","qty":"13"},{"mfg":"Fujitsu","model":"FC9525VAS1","description":"VAS1","qty":"1"},{"mfg":"FUJITSU","model":"FC9580FAN2","description":"","qty":"2"},{"mfg":"FUJITSU","model":"FC9580FP21","description":"","qty":"1"},{"mfg":"FUJITSU","model":"FC9580SF11","description":"","qty":"1"},{"mfg":"FUJITSU","model":"FC9580SF21","description":"","qty":"1"},{"mfg":"Fujitsu","model":"FC9600CCD1","description":"","qty":"9"},{"mfg":"Fujitsu","model":"FC9600DUL2","description":"","qty":"8"},{"mfg":"Fujitsu","model":"FC9600TNE2","description":"\"ADM, FACTR-TIME SLOT UNIT\"","qty":"2"},{"mfg":"Fujitsu","model":"FC9601DPR1","description":"","qty":"1"},{"mfg":"Fujitsu","model":"FC9604REC2","description":"","qty":"2"},{"mfg":"FUJITSU","model":"FC9607CAB4","description":"","qty":"1"},{"mfg":"FUJITSU","model":"FC9607HSB1","description":"","qty":"1"},{"mfg":"FUJITSU","model":"FC9607HSU1","description":"","qty":"2"},{"mfg":"FUJITSU","model":"FC9607HTL1","description":"\"MODULE, FLM2400-HS TRANSMITTER\"","qty":"16"},{"mfg":"FUJITSU","model":"FC9607HTL1","description":"\"MODULE, FLM2400-HS TRANSMITTER\"","qty":"2"},{"mfg":"FUJITSU","model":"FC9607HTL4","description":"","qty":"1"},{"mfg":"Fujitsu","model":"FC9607HTL6","description":"","qty":"4"},{"mfg":"FUJITSU","model":"FC9607MPD1","description":"\"ADM, FLM2400 MICROPROCESSOR PRELOADED W\/ 15.3 SOFTWARE (PL-MP2H240-R1503)\"","qty":"3"},{"mfg":"FUJITSU","model":"FC9607MPD1","description":"\"ADM, FLM2400 MICROPROCESSOR PRELOADED W\/ 15.3 SOFTWARE (PL-MP2H240-R1503)\"","qty":"78"},{"mfg":"FUJITSU","model":"FC9607PWH1","description":"","qty":"35"},{"mfg":"Fujitsu","model":"FC9607SVD1","description":"","qty":"11"},{"mfg":"Fujitsu","model":"FC9608BR31","description":"iss-02","qty":"15"},{"mfg":"Fujitsu","model":"FC9608HCM1","description":"","qty":"3"},{"mfg":"Fujitsu","model":"FC9608HCM1","description":"","qty":"3"},{"mfg":"Fujitsu","model":"FC9608HSD3","description":"","qty":"1"},{"mfg":"Fujitsu","model":"FC9608HSD3","description":"","qty":"1"},{"mfg":"Fujitsu","model":"FC9608HSS1","description":"","qty":"1"},{"mfg":"Fujitsu","model":"FC9608HSS2","description":"","qty":"4"},{"mfg":"Fujitsu","model":"FC9608HSS4","description":"","qty":"3"},{"mfg":"Fujitsu","model":"FC9608MPT9","description":"","qty":"6"},{"mfg":"Fujitsu","model":"FC9608MSD3","description":"MS2T-D31","qty":"17"},{"mfg":"Fujitsu","model":"FC9608PW11","description":"iss-02,03,04","qty":"13"},{"mfg":"Fujitsu","model":"FC9612AWB1","description":"","qty":"27"},{"mfg":"Fujitsu","model":"FC9612ECD1","description":"","qty":"26"},{"mfg":"Fujitsu","model":"FC9612ECD1","description":"","qty":"1"},{"mfg":"Fujitsu","model":"FC9612H3L1","description":"","qty":"2"},{"mfg":"Fujitsu","model":"FC9612LBT2","description":"LC1A-10BT","qty":"1"},{"mfg":"Fujitsu","model":"FC9612LD11","description":"","qty":"2"},{"mfg":"Fujitsu","model":"FC9612LSD1","description":"","qty":"24"},{"mfg":"Fujitsu","model":"FC9612LSD1","description":"","qty":"4"},{"mfg":"Fujitsu","model":"FC9612MST2","description":"LC1A-10BT","qty":"1"},{"mfg":"Fujitsu","model":"FC9612SVD1","description":"","qty":"1"},{"mfg":"Fujitsu","model":"FC9612SVD1","description":"","qty":"2"},{"mfg":"FUJITSU","model":"FC9616MPA1","description":"","qty":"1"},{"mfg":"Fujitsu","model":"FC9616SVD1","description":"","qty":"2"},{"mfg":"Fujitsu","model":"FC9680VT42","description":"","qty":"7"},{"mfg":"FUJITSU","model":"FC9681FSB1","description":"","qty":"1"},{"mfg":"HP","model":"HP17","description":"Tricolor Inkjet Cartridge","qty":"1"},{"mfg":"HP","model":"HP20","description":"Black Inkjet Cartridge","qty":"5"},{"mfg":"HP","model":"HP26","description":"Black Inkjet Cartridge","qty":"1"},{"mfg":"HP","model":"HP29","description":"Black Inkjet Cartridge","qty":"2"},{"mfg":"HP","model":"HPJ4111A","description":"10\/100 Base-T Module for ProCurve 4000M","qty":"100"},{"mfg":"HP","model":"HPJ4121A","description":"ProCurve Switch 4000M w\/Switch Engine Module","qty":"4"},{"mfg":"HP","model":"J2094A","description":"RS-232-C Modem Connect","qty":"2"},{"mfg":"HP","model":"J4812A","description":"Procurve 2515 12x port","qty":"1"},{"mfg":"HP","model":"J4858A","description":"SFP Transciever","qty":"56"},{"mfg":"HP","model":"J4862B","description":"10\/100BT 24 PORT","qty":"5"},{"mfg":"HP","model":"J4887A","description":"4104GL SWITCH","qty":"5"},{"mfg":"HP","model":"JetDirect","description":"Token Ring Card","qty":"1"},{"mfg":"Hynix","model":"PC2-5300F-555-11","description":"2GB  2Rx4","qty":"373"},{"mfg":"Hynix","model":"PC2-6400F-555-11","description":"2GB  2Rx8","qty":"111"},{"mfg":"IDB","model":"DCS3-002-2","description":"Down Converter","qty":"2"},{"mfg":"LNR","model":"506012978-3","description":"DOWNCONVERTER","qty":"1"},{"mfg":"LNR","model":"506012978-3","description":"DOWNCONVERTER","qty":"1"},{"mfg":"LNR","model":"506012979-1","description":"UPCONVERTER","qty":"1"},{"mfg":"LNR","model":"506012979-4","description":"UPCONVERTER","qty":"1"},{"mfg":"Lucent","model":"11120","description":"810-00510-21","qty":"3"},{"mfg":"Lucent","model":"1145B2","description":"","qty":"1"},{"mfg":"Lucent","model":"11590","description":"810-00157-03","qty":"14"},{"mfg":"Lucent","model":"11593","description":"810-00156-01","qty":"3"},{"mfg":"Lucent","model":"11600","description":"810-00342-02","qty":"7"},{"mfg":"Lucent","model":"11711","description":"810-0410-00","qty":"3"},{"mfg":"Lucent","model":"11723","description":"810-00340-04","qty":"3"},{"mfg":"Lucent","model":"11724","description":"810-00348-00","qty":"3"},{"mfg":"Lucent","model":"16E","description":"","qty":"1"},{"mfg":"Lucent","model":"16E2","description":"","qty":"2"},{"mfg":"Lucent","model":"21D-U","description":"107092637  S1:1","qty":"4"},{"mfg":"Lucent","model":"21G2-U","description":"","qty":"1"},{"mfg":"Lucent","model":"22D-U","description":"Board","qty":"5"},{"mfg":"Lucent","model":"22F-U","description":"","qty":"16"},{"mfg":"Lucent","model":"22F2-U","description":"S1:1","qty":"3"},{"mfg":"Lucent","model":"22G3-U","description":"MODULE RU LTWV REGEN 108029778","qty":"4"},{"mfg":"Lucent","model":"22G4-U","description":"MODULE","qty":"1"},{"mfg":"Lucent","model":"23G","description":"CARD","qty":"3"},{"mfg":"Lucent","model":"24G-U","description":"","qty":"2"},{"mfg":"Lucent","model":"26G2-U","description":"107727745","qty":"5"},{"mfg":"Lucent","model":"28G-U","description":"107921900   s1:1","qty":"2"},{"mfg":"Lucent","model":"410AA2","description":"108133232","qty":"12"},{"mfg":"Lucent","model":"414AA","description":"Power Unit","qty":"1"},{"mfg":"Lucent","model":"424AA","description":"","qty":"3"},{"mfg":"Lucent","model":"427AA","description":"106473861   S1:5","qty":"1"},{"mfg":"Lucent","model":"494GA","description":"Power Unit","qty":"1"},{"mfg":"Lucent","model":"495FA","description":"Power Unit","qty":"1"},{"mfg":"Lucent","model":"547A","description":"POWER UNIT","qty":"1"},{"mfg":"Lucent","model":"553B","description":"POWER UNIT","qty":"1"},{"mfg":"Lucent","model":"556C","description":"","qty":"1"},{"mfg":"Lucent","model":"839B5","description":"","qty":"2"},{"mfg":"Lucent","model":"982TN","description":"CARD","qty":"1"},{"mfg":"Lucent","model":"AEK36A","description":"Board","qty":"22"},{"mfg":"Lucent","model":"AKM2C","description":"Board","qty":"1"},{"mfg":"Lucent","model":"AKM53","description":"","qty":"1"},{"mfg":"Lucent","model":"AKM56","description":"S:2","qty":"11"},{"mfg":"Lucent","model":"AKM6","description":"S1:5","qty":"5"},{"mfg":"Lucent","model":"AKM64","description":"105672802","qty":"1"},{"mfg":"Lucent","model":"AKM70","description":"","qty":"1"},{"mfg":"Lucent","model":"AKM90","description":"Board","qty":"4"},{"mfg":"Lucent","model":"AUG3","description":"","qty":"1"},{"mfg":"Lucent","model":"AWP8","description":"S2:3","qty":"2"},{"mfg":"Lucent","model":"AWR12","description":"S1:1","qty":"1"},{"mfg":"Lucent","model":"AWR2C","description":"S1:1","qty":"1"},{"mfg":"Lucent","model":"BBF1B","description":"106543606","qty":"215"},{"mfg":"Lucent","model":"BBF2","description":"","qty":"1"},{"mfg":"Lucent","model":"BBF241","description":"107191157","qty":"4"},{"mfg":"Lucent","model":"BBF250","description":"SAIUN60BAA","qty":"3"},{"mfg":"Lucent","model":"BBF261","description":"MEMORY  SYSTEM UNIT SLC2000 106972128","qty":"4"},{"mfg":"Lucent","model":"BBF2B","description":"SNPQA16AAB","qty":"21"},{"mfg":"Lucent","model":"BBG11B","description":"106008071   S1:1","qty":"2"},{"mfg":"Lucent","model":"BBG12","description":"106409170   S1:1","qty":"13"},{"mfg":"Lucent","model":"BBG2","description":"106439409","qty":"2"},{"mfg":"Lucent","model":"BBG266","description":" SLC2000 VIRTUAL TRIBUTARY 108567124   S2:4","qty":"2"},{"mfg":"Lucent","model":"BBG267","description":"","qty":"1"},{"mfg":"Lucent","model":"BBG268","description":"106943814","qty":"53"},{"mfg":"Lucent","model":"BBG27G","description":"S1:1","qty":"1"},{"mfg":"Lucent","model":"BBG4B","description":"","qty":"1"},{"mfg":"Lucent","model":"BBG5","description":"106633688","qty":"7"},{"mfg":"Lucent","model":"BBG6","description":"106008097   S1:1","qty":"4"},{"mfg":"Lucent","model":"BBG7","description":"107835282","qty":"2"},{"mfg":"Lucent","model":"BBG8B","description":"SYSCTL","qty":"6"},{"mfg":"Lucent","model":"BBR1","description":"","qty":"1"},{"mfg":"Lucent","model":"BCP1","description":"","qty":"4"},{"mfg":"Lucent","model":"BCP2","description":"","qty":"1"},{"mfg":"Lucent","model":"BCP3","description":"","qty":"18"},{"mfg":"Lucent","model":"BCP4","description":"107136574","qty":"10"},{"mfg":"Lucent","model":"BDK270","description":"BANDWITH MANAGEMENT PROCESSOR 106939093  S1:1","qty":"2"},{"mfg":"Lucent","model":"BKF1","description":"S2:5","qty":"1"},{"mfg":"Lucent","model":"BUA6","description":"","qty":"2"},{"mfg":"Lucent","model":"BYB2","description":"","qty":"1"},{"mfg":"Lucent","model":"DIXI-3-R2-DS3","description":"","qty":"24"},{"mfg":"Lucent","model":"DTP101","description":"S1:2","qty":"1"},{"mfg":"Lucent","model":"ED7G050-21","description":"","qty":"1"},{"mfg":"Lucent","model":"ED8C727-30","description":"","qty":"1"},{"mfg":"Lucent","model":"ED8C843-31","description":"","qty":"1"},{"mfg":"Lucent","model":"ED9C023-30","description":"","qty":"1"},{"mfg":"Lucent","model":"FHB2","description":"107649287","qty":"17"},{"mfg":"Lucent","model":"GGC-P230NT1","description":"\"MISC, UNIT NETTERM NT1P 230\"","qty":"1"},{"mfg":"Lucent","model":"KAA5","description":"","qty":"1"},{"mfg":"Lucent","model":"KBN5","description":"","qty":"3"},{"mfg":"Lucent","model":"KBN6","description":"","qty":"1"},{"mfg":"Lucent","model":"KBN8B \/ 1:6","description":"107510828","qty":"2"},{"mfg":"Lucent","model":"KCR4","description":"","qty":"1"},{"mfg":"Lucent","model":"KLU1B","description":"Board","qty":"14"},{"mfg":"Lucent","model":"KLU2","description":"","qty":"1"},{"mfg":"Lucent","model":"KLU3","description":"","qty":"2"},{"mfg":"Lucent","model":"KLW128","description":"","qty":"4"},{"mfg":"Lucent","model":"KTU1","description":"Board","qty":"2"},{"mfg":"Lucent","model":"KTU1B \/ 3:3","description":"108225343","qty":"4"},{"mfg":"Lucent","model":"KTU2","description":"Board","qty":"1"},{"mfg":"Lucent","model":"LAA12","description":"S1:3","qty":"4"},{"mfg":"Lucent","model":"LAA12B","description":"S1:1","qty":"4"},{"mfg":"Lucent","model":"LAA2","description":"S4:8","qty":"1"},{"mfg":"Lucent","model":"LAA21","description":"S2:4","qty":"6"},{"mfg":"Lucent","model":"LAA23B","description":"S1:3  S1:4","qty":"11"},{"mfg":"Lucent","model":"LAA23C","description":"S1:1","qty":"1"},{"mfg":"Lucent","model":"LAA25","description":"SYSMEM","qty":"4"},{"mfg":"Lucent","model":"LAA26","description":"S1:2","qty":"6"},{"mfg":"Lucent","model":"LAA4","description":"S1:5","qty":"2"},{"mfg":"Lucent","model":"LAA5","description":"S1:1","qty":"4"},{"mfg":"Lucent","model":"LEY1","description":"108730102","qty":"6"},{"mfg":"Lucent","model":"LEY10B","description":"","qty":"13"},{"mfg":"Lucent","model":"LEY10BE","description":"","qty":"4"},{"mfg":"Lucent","model":"LEY14","description":"","qty":"3"},{"mfg":"Lucent","model":"LEY15","description":"107978066","qty":"2"},{"mfg":"Lucent","model":"LEY15AE","description":"108730813","qty":"1"},{"mfg":"Lucent","model":"LEY16","description":"","qty":"13"},{"mfg":"Lucent","model":"LEY16AE","description":"","qty":"1"},{"mfg":"Lucent","model":"LEY18","description":"","qty":"18"},{"mfg":"Lucent","model":"LEY1AE","description":"","qty":"2"},{"mfg":"Lucent","model":"LEY4","description":"","qty":"19"},{"mfg":"Lucent","model":"LEY4AE","description":"108734617  S2:4A","qty":"20"},{"mfg":"Lucent","model":"LEY7","description":"","qty":"14"},{"mfg":"Lucent","model":"LLY2BE","description":"","qty":"12"},{"mfg":"Lucent","model":"LPA380","description":"","qty":"10"},{"mfg":"Lucent","model":"LPA416","description":"S4:9","qty":"2"},{"mfg":"Lucent","model":"LPA901","description":"S1:5","qty":"1"},{"mfg":"Lucent","model":"MC3F","description":"","qty":"17"},{"mfg":"Lucent","model":"MC901","description":"","qty":"1"},{"mfg":"Lucent","model":"MC97","description":"","qty":"35"},{"mfg":"Lucent","model":"MZ26A50","description":"","qty":"1"},{"mfg":"Lucent","model":"NJ00675A2","description":"","qty":"2"},{"mfg":"Lucent","model":"NS20N020FD","description":"","qty":"2"},{"mfg":"Lucent","model":"NS23N620CC","description":"","qty":"1"},{"mfg":"Lucent","model":"SN107","description":"","qty":"1"},{"mfg":"Lucent","model":"SN346B","description":"","qty":"2"},{"mfg":"Lucent","model":"SN516B","description":"","qty":"1"},{"mfg":"Lucent","model":"SN516C","description":"","qty":"2"},{"mfg":"Lucent","model":"STGR-LIM-SH-48","description":"0800-0926-001","qty":"2"},{"mfg":"Lucent","model":"T86A","description":"","qty":"2"},{"mfg":"Lucent","model":"TG58C","description":"","qty":"1"},{"mfg":"Lucent","model":"TG60C","description":"108135526","qty":"1"},{"mfg":"Lucent","model":"TG64B","description":"","qty":"3"},{"mfg":"Lucent","model":"TM590","description":" DPLL","qty":"3"},{"mfg":"Lucent","model":"TM657B","description":"","qty":"2"},{"mfg":"Lucent","model":"TM736C","description":"","qty":"3"},{"mfg":"Lucent","model":"TM778","description":"","qty":"2"},{"mfg":"Lucent","model":"TN10","description":"","qty":"1"},{"mfg":"Lucent","model":"TN1009","description":"E5PQ42LAXX","qty":"1"},{"mfg":"Lucent","model":"TN1010","description":"","qty":"1"},{"mfg":"Lucent","model":"TN1034 2","description":"E5PQ42LAXX","qty":"1"},{"mfg":"Lucent","model":"TN1042","description":"E5MQAC2AAA","qty":"2"},{"mfg":"Lucent","model":"TN1042B","description":"","qty":"1"},{"mfg":"Lucent","model":"TN1082B","description":"E5MQABUAAA","qty":"1"},{"mfg":"Lucent","model":"TN1083C","description":"","qty":"1"},{"mfg":"Lucent","model":"TN1086B","description":"","qty":"1"},{"mfg":"Lucent","model":"TN1274B","description":"E5PQ37PAAD","qty":"1"},{"mfg":"Lucent","model":"TN1286B","description":"","qty":"1"},{"mfg":"Lucent","model":"TN1346","description":"E5MQ808AAC","qty":"1"},{"mfg":"Lucent","model":"TN1348","description":"E5PQ54BAAB","qty":"1"},{"mfg":"Lucent","model":"TN1367C","description":"E5MQAEPAAB","qty":"1"},{"mfg":"Lucent","model":"TN1377 5","description":"E5PQ38RAAD","qty":"1"},{"mfg":"Lucent","model":"TN138","description":"104229430","qty":"2"},{"mfg":"Lucent","model":"TN1422","description":"","qty":"1"},{"mfg":"Lucent","model":"TN1611B","description":"E5MQABEAAA","qty":"1"},{"mfg":"Lucent","model":"TN1612B","description":"E5MQAB4AAA","qty":"1"},{"mfg":"Lucent","model":"TN1640B","description":"CNPQAKRAAA","qty":"1"},{"mfg":"Lucent","model":"TN1661","description":"ESPQALWAAA","qty":"1"},{"mfg":"Lucent","model":"TN1800","description":"ESPQANYAAC","qty":"2"},{"mfg":"Lucent","model":"TN1802","description":"E5PQABDAAD","qty":"1"},{"mfg":"Lucent","model":"TN1806","description":"106501703","qty":"2"},{"mfg":"Lucent","model":"TN1842","description":"106945124","qty":"2"},{"mfg":"Lucent","model":"TN1843","description":"106951007","qty":"2"},{"mfg":"Lucent","model":"TN1846","description":"107488736","qty":"8"},{"mfg":"Lucent","model":"TN1873","description":"","qty":"6"},{"mfg":"Lucent","model":"TN220B","description":"","qty":"2"},{"mfg":"Lucent","model":"TN221","description":"103884953","qty":"2"},{"mfg":"Lucent","model":"TN3B","description":"SPPQ10DAXX","qty":"1"},{"mfg":"Lucent","model":"TN56","description":"","qty":"16"},{"mfg":"Lucent","model":"TN5B","description":"SPPQ10DAXX","qty":"1"},{"mfg":"Lucent","model":"TN619","description":"E5PQ41CAAD","qty":"1"},{"mfg":"Lucent","model":"TN61B","description":"","qty":"1"},{"mfg":"Lucent","model":"TN69B","description":"SP3Q05ZAXX","qty":"1"},{"mfg":"Lucent","model":"TN6B","description":"","qty":"1"},{"mfg":"Lucent","model":"TN70B","description":"CNPQACCAXX","qty":"1"},{"mfg":"Lucent","model":"TN70C","description":"SPQQ06NAAA","qty":"1"},{"mfg":"Lucent","model":"TN736","description":"","qty":"1"},{"mfg":"Lucent","model":"TN75C","description":"SPMQ06GAXX","qty":"1"},{"mfg":"Lucent","model":"TN833C","description":"E5MQAC9AAA","qty":"2"},{"mfg":"Lucent","model":"TN856C","description":"106075377","qty":"2"},{"mfg":"Lucent","model":"TN867","description":"103654505","qty":"2"},{"mfg":"Lucent","model":"TN870","description":"E5MQ803AXX","qty":"1"},{"mfg":"Lucent","model":"TN883","description":"ESMQ43KAAE","qty":"1"},{"mfg":"Lucent","model":"TN884C","description":"107283657","qty":"1"},{"mfg":"Lucent","model":"TN886","description":"ESMQ43KAAE","qty":"1"},{"mfg":"Lucent","model":"TN9","description":"SP3Q03GAXX","qty":"4"},{"mfg":"Lucent","model":"TN914","description":"CCPQ026AAC","qty":"1"},{"mfg":"Lucent","model":"TN915","description":"Board","qty":"3"},{"mfg":"Lucent","model":"TN918","description":"CCPQ021AXX","qty":"9"},{"mfg":"Lucent","model":"TNT-SL-CE1-750-C","description":"0800-0411-053","qty":"1"},{"mfg":"Lucent","model":"TNT-SL-E10-100","description":"0800-0433-001","qty":"1"},{"mfg":"Lucent","model":"TSM8","description":"Back","qty":"1"},{"mfg":"Lucent","model":"TSM8","description":"Front","qty":"1"},{"mfg":"Lucent","model":"UM71","description":"","qty":"1"},{"mfg":"Lucent","model":"UM74D","description":"108229162","qty":"2"},{"mfg":"Lucent","model":"UM76","description":"","qty":"2"},{"mfg":"Lucent","model":"UN11C","description":"SPPQ00NAXX","qty":"1"},{"mfg":"Lucent","model":"UN122","description":"CCPQ018AXX","qty":"1"},{"mfg":"Lucent","model":"UN122C","description":"","qty":"16"},{"mfg":"Lucent","model":"UN123B","description":"CCPQ028AXX","qty":"16"},{"mfg":"Lucent","model":"UN133B","description":"SPPQ00SAXX","qty":"1"},{"mfg":"Lucent","model":"UN135","description":"","qty":"1"},{"mfg":"Lucent","model":"UN1C","description":"","qty":"1"},{"mfg":"Lucent","model":"UN21B","description":"SPQ3QI0JAXX","qty":"1"},{"mfg":"Lucent","model":"UN221","description":"","qty":"1"},{"mfg":"Lucent","model":"UN22C","description":"SP3Q11PAXX","qty":"1"},{"mfg":"Lucent","model":"UN23C","description":"SP3Q01LAXX","qty":"1"},{"mfg":"Lucent","model":"UN25B","description":"SP3Q01AAXX","qty":"2"},{"mfg":"Lucent","model":"UN2B","description":"SPMQ57JAXX","qty":"1"},{"mfg":"Lucent","model":"UN304","description":"","qty":"1"},{"mfg":"Lucent","model":"UN306","description":"E5PQ00FAAB","qty":"1"},{"mfg":"Lucent","model":"UN307","description":"E5PQASLAAB","qty":"1"},{"mfg":"Lucent","model":"UN310","description":"","qty":"1"},{"mfg":"Lucent","model":"UN33B","description":"SP3Q10NAXX","qty":"3"},{"mfg":"Lucent","model":"UN363 \/ 1:4","description":"106456981","qty":"3"},{"mfg":"Lucent","model":"UN395B","description":"107678559","qty":"2"},{"mfg":"Lucent","model":"UN396","description":"106950991","qty":"2"},{"mfg":"Lucent","model":"UN3B","description":"SPQ11LAXX","qty":"2"},{"mfg":"LUCENT","model":"UN43D","description":"SPPQRASAAA","qty":"1"},{"mfg":"LUCENT","model":"UN45E","description":"SP3QRASAAA","qty":"1"},{"mfg":"LUCENT","model":"UN46D","description":"SP3Q01WAXX","qty":"1"},{"mfg":"LUCENT","model":"UN48B","description":"","qty":"1"},{"mfg":"Lucent","model":"UN503","description":"","qty":"1"},{"mfg":"Lucent","model":"UN515B","description":"","qty":"1"},{"mfg":"Lucent","model":"UN517B","description":"E5MQAFYAAA","qty":"1"},{"mfg":"Lucent","model":"UN518","description":"","qty":"3"},{"mfg":"Lucent","model":"UN538","description":"107073009","qty":"1"},{"mfg":"Lucent","model":"UN539","description":"E5PQATDAAA","qty":"1"},{"mfg":"Lucent","model":"UN539B","description":"108162454","qty":"5"},{"mfg":"Lucent","model":"UN55","description":"107077000","qty":"1"},{"mfg":"Lucent","model":"UN553","description":"107077000","qty":"5"},{"mfg":"Lucent","model":"UN582B","description":"","qty":"8"},{"mfg":"Lucent","model":"UN584","description":"107183691","qty":"2"},{"mfg":"Lucent","model":"UN588","description":"108767393","qty":"2"},{"mfg":"Lucent","model":"UN590","description":"108627365","qty":"2"},{"mfg":"Lucent","model":"UN59C","description":"SPPQ00RAXX","qty":"1"},{"mfg":"Lucent","model":"UN64","description":"SP3Q02RAAF","qty":"1"},{"mfg":"Lucent","model":"UN6B","description":"","qty":"1"},{"mfg":"Lucent","model":"UN71C","description":"107872293","qty":"3"},{"mfg":"Lucent","model":"UN9B","description":"SPQ301EAXX","qty":"2"},{"mfg":"Lucent","model":"WSA001","description":"","qty":"1"},{"mfg":"Maxtor","model":"9DP14G-326","description":"320 GB HD","qty":"3"},{"mfg":"Mentat Sky","model":"XR 10","description":"SKY X GATEWAY","qty":"1"},{"mfg":"Netaccess","model":"T96-6028-0","description":"PRI-ISA 2T","qty":"1"},{"mfg":"Nortel","model":"NT0H0102","description":"","qty":"1"},{"mfg":"Nortel","model":"NT0H01KC","description":"","qty":"1"},{"mfg":"Nortel","model":"NT0H02AB","description":"OC-48 OCLD","qty":"1"},{"mfg":"Nortel","model":"NT0H02LA","description":"","qty":"2"},{"mfg":"Nortel","model":"NT0H02LC","description":"","qty":"1"},{"mfg":"Nortel","model":"NT0H30LA","description":"","qty":"1"},{"mfg":"Nortel","model":"NT0H55AA","description":"\"MODULE, MP ETHERNET CARD LUI 5200 TECHNOLOGY\"","qty":"1"},{"mfg":"Nortel","model":"NT0H56AA","description":"\"MODULE, MP ETHERNET CARD LUI 5200 TECHNOLOGY\"","qty":"2"},{"mfg":"Nortel","model":"NT0H57AA","description":"\"MODULE, MP OMX CARD OMX IF 5200 TECHNOLOGY\"","qty":"1"},{"mfg":"Nortel","model":"NT0H57BB","description":"\"MODULE, MP ETHERNET CARD LUI 5200 TECHNOLOGY\"","qty":"1"},{"mfg":"Nortel","model":"NT0H58AA","description":"\"MODULE, MP ETHERNET CARD LUI 5200 TECHNOLOGY\"","qty":"1"},{"mfg":"Nortel","model":"NT1J22AA","description":"","qty":"1"},{"mfg":"Nortel","model":"NT2A11DA","description":"REV 04 unit","qty":"3"},{"mfg":"Nortel","model":"NT5C15AA","description":"","qty":"1"},{"mfg":"Nortel","model":"NT5E0102","description":"","qty":"1"},{"mfg":"Nortel","model":"NT5E14CA","description":"","qty":"10"},{"mfg":"NORTEL","model":"NT6D40BA","description":"#N\/A","qty":"1"},{"mfg":"Nortel","model":"NT6H71BA","description":"","qty":"1"},{"mfg":"NORTEL","model":"NT6X50AB","description":"","qty":"14"},{"mfg":"Nortel","model":"NT7B62GB-93","description":"Auto ranging power supply","qty":"1"},{"mfg":"Nortel","model":"NT7B75GA","description":"","qty":"1"},{"mfg":"NORTEL","model":"NT7E01FB","description":"ADM,0C-3 FULL HEIGHT CARD","qty":"13"},{"mfg":"NORTEL","model":"NT7E01GA","description":"\"WDM,  OC-3 LR NETWORK INTERFACE 1310NM\"","qty":"2"},{"mfg":"NORTEL","model":"NT7E01GB","description":"\"WDM,  OC-3 LR NETWORK INTERFACE 1310NM\"","qty":"2"},{"mfg":"Nortel","model":"NT7E02EB","description":"OC-12 LR 1310 Ring IF (FC) (R47)","qty":"4"},{"mfg":"Nortel","model":"NT7E02FB","description":"OC-12 LR 1310 Ring IF (FC)","qty":"14"},{"mfg":"Nortel","model":"NT7E02FC","description":"OC-12 LR 1310 Ring IF (FC)","qty":"3"},{"mfg":"Nortel","model":"NT7E02FD","description":"OC-12 LR 1310 Ring IF (FC)","qty":"1"},{"mfg":"Nortel","model":"NT7E02PB","description":"IR 1310 Interface (R17)(R16)","qty":"7"},{"mfg":"Nortel","model":"NT7E04CA","description":"DS1 Sync VT Mapper (R11)","qty":"1"},{"mfg":"NORTEL","model":"NT7E04EA","description":"FDN600 DS1\/VT MAPPER","qty":"5"},{"mfg":"Nortel","model":"NT7E08AA","description":"DS3 STS-1 Mapper","qty":"32"},{"mfg":"Nortel","model":"NT7E09AA","description":"STS-1 I\/F (Rev 12)","qty":"3"},{"mfg":"Nortel","model":"NT7E20CC","description":"Shelf Proc","qty":"3"},{"mfg":"Nortel","model":"NT7E20CD","description":"","qty":"5"},{"mfg":"Nortel","model":"NT7E20GD","description":"\"ADM, CARD SHELF PROCESSOR W\/ SYNC MESS ETHERNET\"","qty":"4"},{"mfg":"Nortel","model":"NT7E23AA","description":"Maint IF","qty":"2"},{"mfg":"NORTEL","model":"NT7E24AC","description":"","qty":"2"},{"mfg":"Nortel","model":"NT7E25AA","description":"Order Wire (Rev 4)","qty":"1"},{"mfg":"Nortel","model":"NT7E27AA","description":"Ext Sync IF (R10)","qty":"2"},{"mfg":"Nortel","model":"NT7E27BA","description":"\"ADM, CARD INTERFACE EXT SYNC C\/T 584847\"","qty":"1"},{"mfg":"NORTEL","model":"NT7E27DA","description":"ADM, INTERFACE EXTERNAL SYNCHRONIZATION","qty":"4"},{"mfg":"NORTEL","model":"NT7E27EA","description":"Rel. 08","qty":"1"},{"mfg":"Nortel","model":"NT7E35AA","description":"OC-12 Ring Loopbk (16)(17)","qty":"1"},{"mfg":"Nortel","model":"NT7E36AA","description":"OC12 Ring Overhd Bridge","qty":"3"},{"mfg":"Nortel","model":"NT7E39AA","description":"","qty":"1"},{"mfg":"Nortel","model":"NT7H62XA","description":"Board","qty":"3"},{"mfg":"Nortel","model":"NT7H63AA","description":"Board","qty":"16"},{"mfg":"Nortel","model":"NT7H66AB","description":"Board","qty":"2"},{"mfg":"Nortel","model":"NT7H71XA","description":"Board","qty":"18"},{"mfg":"Nortel","model":"NT7H85XA","description":"MODULE FMT150 DS3 TRANSLATOR","qty":"2"},{"mfg":"Nortel","model":"NT8D14BB","description":"","qty":"2"},{"mfg":"NORTEL","model":"NT8E01FC","description":"OC-48","qty":"1"},{"mfg":"Nortel","model":"NT8E01NG","description":"","qty":"1"},{"mfg":"Nortel","model":"NT8E03CB","description":"","qty":"3"},{"mfg":"NORTEL","model":"NT8E05CC","description":"\"ADM, OC-48 DEMULTIPLEXER LINEAR\"","qty":"5"},{"mfg":"NORTEL","model":"NT8E08BD","description":"MODULE","qty":"1"},{"mfg":"Nortel","model":"NT8E15AA","description":"Switcher 24 (R04)","qty":"4"},{"mfg":"NORTEL","model":"NT8E18AC","description":"ADM CONTROLLER OC-48 SWITCH 48 DS-3\/STS-1","qty":"2"},{"mfg":"NORTEL","model":"NT8E31EA","description":"","qty":"1"},{"mfg":"Nortel","model":"NT8E85MC","description":"","qty":"8"},{"mfg":"NORTEL","model":"NT9X14DB","description":"R16","qty":"1"},{"mfg":"NORTEL","model":"NT9X26AB","description":"","qty":"2"},{"mfg":"Nortel","model":"NT9X30AA","description":"DMS-100E PWR CONVR","qty":"1"},{"mfg":"Nortel","model":"NT9X35CA","description":"R10","qty":"4"},{"mfg":"NORTEL","model":"NT9X53AC","description":"R10","qty":"2"},{"mfg":"NORTEL","model":"NTCA21AA","description":"R03","qty":"1"},{"mfg":"NORTEL","model":"NTCA24AA","description":"ADM, 4 FIBER SWITCH MODULE","qty":"5"},{"mfg":"NORTEL","model":"NTCA26AA","description":"WDM\/ADM, HDX65 SWITCH MODULE 65GBS *A0762473","qty":"4"},{"mfg":"NORTEL","model":"NTCA31BA","description":"ADM, OC-12 TRIBUTARY TX\/RX 1310 NM FC","qty":"19"},{"mfg":"NORTEL","model":"NTCA31BC","description":"ADM, C-12 TRIBUTARY TX\/RX 1310NM SC","qty":"9"},{"mfg":"NORTEL","model":"NTCA34KA","description":"ADM, C-12 TRIBUTARY TX\/RX 1310NM SC","qty":"1"},{"mfg":"Nortel","model":"NTCA36AA","description":"","qty":"1"},{"mfg":"NORTEL","model":"NTCA40AA","description":"WDM\/ADM BREAKER\/FILTER MODULE","qty":"11"},{"mfg":"NORTEL","model":"NTCA40BA","description":"OC-192 BREAKER MODULE","qty":"14"},{"mfg":"NORTEL","model":"NTCA41BA","description":"FDN2400 SHLF PROCR","qty":"20"},{"mfg":"NORTEL","model":"NTCA42AA","description":"Board","qty":"2"},{"mfg":"Nortel","model":"NTCA44AA","description":"Board","qty":"4"},{"mfg":"Nortel","model":"NTCA45AA","description":"Board","qty":"11"},{"mfg":"Nortel","model":"NTCA47AA","description":"Board","qty":"1"},{"mfg":"NORTEL","model":"NTCA49AB","description":"OC-192 SWITCH FILLER   rel-04","qty":"1"},{"mfg":"NORTEL","model":"NTCA53AA","description":"","qty":"3"},{"mfg":"NORTEL","model":"NTCA79AA","description":"ADM, OC-192 CONSUMABLE SPARES","qty":"100"},{"mfg":"Nortel","model":"NTCC13BB","description":"","qty":"6"},{"mfg":"NORTEL","model":"NTDK23AA","description":"11","qty":"1"},{"mfg":"NORTEL","model":"NTDK78AA","description":"11","qty":"1"},{"mfg":"NORTEL","model":"NTDY30AA","description":"CVX,SERVICE MODULE FOR 96 MODEM\/ISDN CARD REF AC (NTDY40AA)","qty":"1"},{"mfg":"NORTEL","model":"NTDY36AA","description":"","qty":"2"},{"mfg":"NORTEL","model":"NTDY40AC","description":"CVX,SERVICE MODULE FOR 96 MODEM\/ISDN CARD REF AC (NTDY40AA)","qty":"7"},{"mfg":"NORTEL","model":"NTDY40CA","description":"CVX,SERVICE MODULE FOR 102 MODEM\/ISDN CARD REF CA (NTDY40CB)","qty":"1"},{"mfg":"NORTEL","model":"NTEB20AA","description":"#N\/A","qty":"1"},{"mfg":"NORTEL","model":"NTEU10AA","description":"WDM\/ADM, STM1 TRIBUTARY CARD","qty":"1"},{"mfg":"NORTEL","model":"NTEX22BB","description":"Board","qty":"2"},{"mfg":"Nortel","model":"NTFL04GC","description":"R02","qty":"1"},{"mfg":"NORTEL","model":"NTFN18DA","description":"Board","qty":"1"},{"mfg":"NORTEL","model":"NTFN18FA","description":"Board","qty":"1"},{"mfg":"NORTEL","model":"NTFN33GA","description":"Board","qty":"1"},{"mfg":"NORTEL","model":"NTFP18IA","description":"Board","qty":"1"},{"mfg":"NORTEL","model":"NTFP38HA","description":"02","qty":"1"},{"mfg":"NORTEL","model":"NTFP80BA","description":"04","qty":"1"},{"mfg":"NORTEL","model":"NTJT28BA","description":"","qty":"2"},{"mfg":"NORTEL","model":"NTK505FB","description":"11","qty":"2"},{"mfg":"Nortel","model":"NTLX08AA","description":"","qty":"1"},{"mfg":"Nortel","model":"NTMX77AA","description":"Board","qty":"1"},{"mfg":"NORTEL","model":"NTN380DB","description":"","qty":"1"},{"mfg":"Nortel","model":"NTN405AA","description":"EC-1 Mapper","qty":"7"},{"mfg":"Nortel","model":"NTN410BA","description":"VT X Connect VTX","qty":"4"},{"mfg":"Nortel","model":"NTN410DA","description":"VT X Connect VTX 12\/3 (R03)","qty":"2"},{"mfg":"Nortel","model":"NTN412AA","description":"Protection Switch Controller","qty":"1"},{"mfg":"Nortel","model":"NTN413AA","description":"","qty":"2"},{"mfg":"Nortel","model":"NTN421BA","description":"Network Processor","qty":"6"},{"mfg":"Nortel","model":"NTN422AA","description":"Network Processor","qty":"11"},{"mfg":"Nortel","model":"NTN430AA","description":"DS1 Mapper","qty":"29"},{"mfg":"Nortel","model":"NTN431AA","description":"DS3 Mapper (R02)","qty":"2"},{"mfg":"Nortel","model":"NTN433BB","description":"","qty":"1"},{"mfg":"Nortel","model":"NTN438AA","description":"DS1 Mapper  R04","qty":"6"},{"mfg":"Nortel","model":"NTN454AA","description":"","qty":"1"},{"mfg":"Nortel","model":"NTN455AA","description":"","qty":"1"},{"mfg":"Nortel","model":"NTN458HC","description":"Board","qty":"1"},{"mfg":"Nortel","model":"NTN484LG","description":"DS1 Mapper  ntn424bh","qty":"2"},{"mfg":"Nortel","model":"NTN484LP","description":"DS1 Mapper  ntn424bh","qty":"1"},{"mfg":"Nortel","model":"NTN484PC","description":"DS1 Mapper  ntn424bh","qty":"1"},{"mfg":"NORTEL","model":"NTNQ37AA","description":"Board","qty":"1"},{"mfg":"NORTEL","model":"NTOH57BB","description":"#N\/A","qty":"2"},{"mfg":"Nortel","model":"NTRX50NK","description":"R01","qty":"1"},{"mfg":"NORTEL","model":"NTT861AF","description":"\"WDM, CPL CMD8 GR6 W\/ MUX EDFA AND AM 1U\"","qty":"1"},{"mfg":"NORTEL","model":"NTT861AG","description":"\"WDM, CPL CMD8 GR7 W\/ MUX EDFA AND AM 1U\"","qty":"1"},{"mfg":"Nortel","model":"NTWA00AA","description":"","qty":"1"},{"mfg":"Nortel","model":"NTZK16BA35","description":"Phone","qty":"24"},{"mfg":"Nortel","model":"NTZK16CA35","description":"Phone","qty":"72"},{"mfg":"Optimux  RAD","model":"1680080000","description":"OP-1551\/48\/R","qty":"3"},{"mfg":"Pairgain","model":"MMG220","description":"","qty":"1"},{"mfg":"RSI","model":"UCS13-002-2","description":"Up Converter","qty":"1"},{"mfg":"Samsung","model":"PC2-5300F-555-11-E0","description":"2GB  2Rx4","qty":"64"},{"mfg":"Samsung","model":"PC2-6400F-555-11-E0","description":"2GB  2Rx4","qty":"100"},{"mfg":"Scientific Atlantic","model":"Antenna","description":"11M C-band 4-port feed antenna","qty":"1"},{"mfg":"Seagate","model":"9BD143-304","description":"250GB SATA Hard Drive","qty":"14"},{"mfg":"Seagate","model":"9BJ148-305","description":"750 GB HD","qty":"1"},{"mfg":"Seagate","model":"9BJ148-308","description":"750 GB HD","qty":"1"},{"mfg":"Seagate","model":"9BJ148-561","description":"750 GB HD","qty":"1"},{"mfg":"Seagate","model":"9BL148-301","description":"750 GB HD","qty":"12"},{"mfg":"Seagate","model":"ST3250624AS","description":"250GB SATA Hard Drive","qty":"16"},{"mfg":"StorCase","model":"S10A172","description":"Loaded with 146 GB Drives","qty":"1"},{"mfg":"Sumitomo Electronics","model":"SCP6844-GL-ZWE","description":"GBIC","qty":"14"},{"mfg":"Tektronix","model":"VM 700T","description":"Video Measurement Set Turbo","qty":"2"},{"mfg":"Telect","model":"010-0000-1701","description":"","qty":"5"},{"mfg":"TELECT","model":"010-0156-0623","description":"","qty":"1"},{"mfg":"Telect","model":"010-5008-0001","description":"8 POS WALLMOUNT DSX 1 PANEL","qty":"3"},{"mfg":"Telect","model":"010-8228-0002","description":"","qty":"2"},{"mfg":"Thunder-server","model":"K8SRE S2891","description":"AMD 2400Mhz 2 CPU  8GB Ram 4 banks 8 slots","qty":"22"},{"mfg":"TTC","model":"T-Berd 224","description":"PCM Analyzer","qty":"1"},{"mfg":"Vertex","model":"Antenna","description":"6.1M ku-band 2-port linear feed antenna","qty":"1"},{"mfg":"Vertex","model":"Antenna","description":"9M Ku-Band 4-port Ku-Band Linear feed Antenna","qty":"1"},{"mfg":"XICOM","model":"XTRD-2000C","description":"TWTA","qty":"1"}]}